rt_logger/__init__.py
rt_logger/custom_logger.py
rt_logger/level_based_formater.py
rt_logger/logger.py
rt_logger/py.typed
rt_logger/stream_handler.py
rt_logger-0.1.0.dist-info/LICENSE
rt_logger-0.1.0.dist-info/METADATA
rt_logger-0.1.0.dist-info/WHEEL
rt_logger-0.1.0.dist-info/top_level.txt
rt_logger-0.1.0.dist-info/RECORD
