Metadata-Version: 2.1
Name: rt-logger
Version: 0.1.0
Summary: A custom logger for cli based apps with colors
Author-email: Rune Tech <runetech2024@gmail.com>
License: The MIT License (MIT)
Project-URL: Homepage, https://github.com/runetech0/cli-logger
Project-URL: github, https://github.com/runetech0/cli-logger
Keywords: python,logging,logger
Requires-Python: >=3.11
License-File: LICENSE
Requires-Dist: colorama >=0.4.6
